TFBind/__init__.py
TFBind/nuc_model.py
TFBind/nuc_utils.py
TFBind/data/dict.txt
TFBind/data/length.txt
TFBind/use_model/nuc_20.pth
tfbind-0.6.0.dist-info/licenses/LICENSE
tfbind-0.6.0.dist-info/METADATA
tfbind-0.6.0.dist-info/WHEEL
tfbind-0.6.0.dist-info/top_level.txt
tfbind-0.6.0.dist-info/RECORD
