Metadata-Version: 2.4
Name: TFBind
Version: 0.6.0
Summary: Predict whether the transcription factor protein sequence binds to the DNA gene sequence
Home-page: https://github.com/jingpengLiu/TFBind
Author: JingPeng Liu
Author-email: 15313226223@163.com
Classifier: Programming Language :: Python :: 3
Classifier: License :: OSI Approved :: MIT License
Classifier: Operating System :: OS Independent
Requires-Python: >=3.11
License-File: LICENSE
Dynamic: author
Dynamic: author-email
Dynamic: classifier
Dynamic: description
Dynamic: description-content-type
Dynamic: home-page
Dynamic: license-file
Dynamic: requires-python
Dynamic: summary
